anemoi_env/__init__.py
anemoi_env-2026.2.0.dist-info/METADATA
anemoi_env-2026.2.0.dist-info/WHEEL
anemoi_env-2026.2.0.dist-info/licenses/AUTHORS
anemoi_env-2026.2.0.dist-info/licenses/LICENSE
anemoi_env-2026.2.0.dist-info/RECORD
