Metadata-Version: 2.4
Name: anemoi-env
Version: 2026.2.0
Summary: Provides a reproducible, versioned Python environment for Anemoi experiments.
License: BSD-3-Clause
License-File: AUTHORS
License-File: LICENSE
Author: Hugues de Laroussilhe
Author-email: hugues.delaroussilhe@meteoswiss.ch
Requires-Python: >=3.11,<3.13
Classifier: License :: OSI Approved :: BSD License
Classifier: Programming Language :: Python :: 3
Classifier: Programming Language :: Python :: 3.11
Classifier: Programming Language :: Python :: 3.12
Requires-Dist: anemoi-datasets
Requires-Dist: anemoi-graphs
Requires-Dist: anemoi-inference
Requires-Dist: anemoi-models
Requires-Dist: anemoi-registry
Requires-Dist: anemoi-training
Requires-Dist: anemoi-utils
